harshCrypto/__init__.py
harshCrypto/harshCrypto.py
harshCrypto-1.0.0.dist-info/LICENCE
harshCrypto-1.0.0.dist-info/METADATA
harshCrypto-1.0.0.dist-info/WHEEL
harshCrypto-1.0.0.dist-info/top_level.txt
harshCrypto-1.0.0.dist-info/RECORD
