Metadata-Version: 2.1
Name: harshCrypto
Version: 1.0.0
Summary: A simple module for file encryption and decryption of the file
Home-page: https://github.com/Geeta-Tech/windows-files-locker
Author: Harsh Yadav
Author-email: harshlms.dev@gmail.com
Classifier: Programming Language :: Python :: 3
Classifier: License :: OSI Approved :: MIT License
Classifier: Operating System :: OS Independent
Requires-Python: >=3.6
License-File: LICENCE
Requires-Dist: cryptography>=3.0
